easyolo/__init__.py
easyolo/easyolo.py
easyolo-0.1.dist-info/METADATA
easyolo-0.1.dist-info/WHEEL
easyolo-0.1.dist-info/top_level.txt
easyolo-0.1.dist-info/RECORD
