Metadata-Version: 2.1
Name: easyolo
Version: 0.1
Summary: A Simple YOLO Implementation for Object Detection
Home-page: https://github.com/IMApurbo/easyolo
Author: AKM Korishee Apurbo
Author-email: bandinvisible8@gmail.com
Classifier: Programming Language :: Python :: 3
Classifier: License :: OSI Approved :: MIT License
Classifier: Operating System :: OS Independent
Requires-Python: >=3.6
Requires-Dist: ultralytics>=8.0.0
Requires-Dist: opencv-python>=4.5.0
Requires-Dist: torch>=1.7.0
Requires-Dist: scikit-learn>=0.24.0
Requires-Dist: pillow>=8.0.0
